yudu/__init__.py
yudu-0.1.1.dist-info/DESCRIPTION.rst
yudu-0.1.1.dist-info/METADATA
yudu-0.1.1.dist-info/RECORD
yudu-0.1.1.dist-info/WHEEL
yudu-0.1.1.dist-info/metadata.json
yudu-0.1.1.dist-info/top_level.txt
