Metadata-Version: 2.0
Name: yudu
Version: 0.1.1
Summary: Onion Data Yudu Project
Home-page: http://github.com/ronfe/yudu
Author: ronfe
Author-email: hongfei@guanghe.tv
License: MIT
Platform: UNKNOWN
